{
  "type": "FeatureCollection",
  "name": "imagens_pontos",
  "crs": {
    "type": "name",
    "properties": {
      "name": "urn:ogc:def:crs:OGC:1.3:CRS84"
    }
  },
  "features": [
    {
      "type": "Feature",
      "id": "20260209_083702.jpg",
      "properties": {
        "nome": "20260209_083702",
        "arquivo": "20260209_083702.jpg",
        "caminho": "IMGS/20260209_083702.jpg",
        "lat": -6.501281666666666,
        "lon": -49.70373138888889,
        "latlon": "-6.501282, -49.703731",
        "utm": "22M 643333 9281199",
        "utm_zone": 22,
        "utm_band": "M",
        "utm_easting": 643333,
        "utm_northing": 9281199,
        "utm_hemisphere": "S",
        "data": "09/02/2026",
        "horario": "08:37",
        "legenda": "Aequeólogo acompanhando ",
        "hash_md5": null,
        "hash_sha256": "3acc3fb402a244354f3ee8b602a5e3ed4a8900b8b674c9b1d653034a1b967a2d",
        "origem_coordenadas": "EXIF",
        "duplicata_local_sha256": false,
        "grupo_duplicata_sha256": ""
      },
      "geometry": {
        "type": "Point",
        "coordinates": [
          -49.70373138888889,
          -6.501281666666666
        ]
      }
    },
    {
      "type": "Feature",
      "id": "20260209_083618.jpg",
      "properties": {
        "nome": "20260209_083618",
        "arquivo": "20260209_083618.jpg",
        "caminho": "IMGS/20260209_083618.jpg",
        "lat": -6.501316388888889,
        "lon": -49.703699722222225,
        "latlon": "-6.501316, -49.703700",
        "utm": "22M 643336 9281195",
        "utm_zone": 22,
        "utm_band": "M",
        "utm_easting": 643336,
        "utm_northing": 9281195,
        "utm_hemisphere": "S",
        "data": "09/02/2026",
        "horario": "08:36",
        "legenda": "Limpeza de sump",
        "hash_md5": null,
        "hash_sha256": "0283a3e0b8b69a3c2aaac2d14d338c79254ce4ea8ecba8f8aa4f8dca70b35b72",
        "origem_coordenadas": "EXIF",
        "duplicata_local_sha256": false,
        "grupo_duplicata_sha256": ""
      },
      "geometry": {
        "type": "Point",
        "coordinates": [
          -49.703699722222225,
          -6.501316388888889
        ]
      }
    },
    {
      "type": "Feature",
      "id": "20260209_083514.jpg",
      "properties": {
        "nome": "20260209_083514",
        "arquivo": "20260209_083514.jpg",
        "caminho": "IMGS/20260209_083514.jpg",
        "lat": -6.501313333333333,
        "lon": -49.703879722222226,
        "latlon": "-6.501313, -49.703880",
        "utm": "22M 643316 9281195",
        "utm_zone": 22,
        "utm_band": "M",
        "utm_easting": 643316,
        "utm_northing": 9281195,
        "utm_hemisphere": "S",
        "data": "09/02/2026",
        "horario": "08:35",
        "legenda": "Limpeza de sump",
        "hash_md5": null,
        "hash_sha256": "c4f9fee42e66deeb4755c0655779c2260aada2491efd9b29ee66293ed7a4a59e",
        "origem_coordenadas": "EXIF",
        "duplicata_local_sha256": false,
        "grupo_duplicata_sha256": ""
      },
      "geometry": {
        "type": "Point",
        "coordinates": [
          -49.703879722222226,
          -6.501313333333333
        ]
      }
    },
    {
      "type": "Feature",
      "id": "20260209_090018.jpg",
      "properties": {
        "nome": "20260209_090018",
        "arquivo": "20260209_090018.jpg",
        "caminho": "IMGS/20260209_090018.jpg",
        "lat": -6.501396388888889,
        "lon": -49.70404305555556,
        "latlon": "-6.501396, -49.704043",
        "utm": "22M 643298 9281186",
        "utm_zone": 22,
        "utm_band": "M",
        "utm_easting": 643298,
        "utm_northing": 9281186,
        "utm_hemisphere": "S",
        "data": "09/02/2026",
        "horario": "09:00",
        "legenda": "Limpeza de sump",
        "hash_md5": null,
        "hash_sha256": "29f6b5f24077dc6f3af551856e33f128de459423bcf1f9e475b126ee1f3232e7",
        "origem_coordenadas": "EXIF",
        "duplicata_local_sha256": false,
        "grupo_duplicata_sha256": ""
      },
      "geometry": {
        "type": "Point",
        "coordinates": [
          -49.70404305555556,
          -6.501396388888889
        ]
      }
    }
  ],
  "ficha": {
    "id": "MLFBXCM4",
    "dataCampo": "2026-02-09",
    "horaIni": "07:00",
    "horaFim": "17:00",
    "atividade": "Monitoramento",
    "categoria": "ADA",
    "projeto": "Santa Lúcia ",
    "coordCampo": "Cícero Oliveira ",
    "arqResp": "Cícero Oliveira ",
    "tipoAcao": "Limpeza de sump",
    "clima": "nublado",
    "vegetacao": "Entorno do sump composto por floresta nativa",
    "relevo": "Média vertente ",
    "solo": "Argiloarenoso",
    "vestigios": "NAO",
    "coleta": "NAO",
    "desc": "Área com entorno composto por floresta nativa de grande e médio porte.",
    "obs": "Durante acompanhamento, não evidenciamos materialidade aequeólogica ",
    "modeloDocx": "MONITORAMENTO",
    "status": "COMPLETED",
    "imagens_sem_gps": []
  }
}